README.rst
setup.py
Conntext.egg-info/PKG-INFO
Conntext.egg-info/SOURCES.txt
Conntext.egg-info/dependency_links.txt
Conntext.egg-info/not-zip-safe
Conntext.egg-info/top_level.txt
conntext/__init__.py
conntext/conntext.py