Metadata-Version: 1.1
Name: Conntext
Version: 0.1.2
Summary: Context managers for secure and atomic database connectivity
Home-page: https://github.com/microamp/conntext
Author: James Nah
Author-email: sangho.nah@gmail.com
License: GNU LESSER GENERAL PUBLIC LICENSE
